aiolago/__init__.py
aiolago/client.py
aiolago/routes.py
aiolago/version.py
aiolago/schemas/__init__.py
aiolago/schemas/add_on.py
aiolago/schemas/applied_add_on.py
aiolago/schemas/applied_coupon.py
aiolago/schemas/billable_metric.py
aiolago/schemas/coupon.py
aiolago/schemas/customer.py
aiolago/schemas/event.py
aiolago/schemas/invoice.py
aiolago/schemas/organization.py
aiolago/schemas/plan.py
aiolago/schemas/subscription.py
aiolago/schemas/wallet.py
aiolago/schemas/wallet_transaction.py
aiolago/schemas/webhooks.py
aiolago/types/__init__.py
aiolago/types/base.py
aiolago/types/errors.py
aiolago/utils/__init__.py
aiolago/utils/config.py
aiolago/utils/helpers.py
aiolago/utils/logs.py
aiolago-0.0.8.dist-info/LICENSE
aiolago-0.0.8.dist-info/METADATA
aiolago-0.0.8.dist-info/WHEEL
aiolago-0.0.8.dist-info/top_level.txt
aiolago-0.0.8.dist-info/RECORD
