Metadata-Version: 2.1
Name: aiolago
Version: 0.0.8
Summary: Unofficial Asyncronous Python Client for Lago
Home-page: https://github.com/GrowthEngineAI/aiolago
Author: Tri Songz
Author-email: ts@growthengineai.com
License: MIT License
Classifier: Intended Audience :: Developers
Classifier: License :: OSI Approved :: MIT License
Classifier: Programming Language :: Python :: 3.7
Classifier: Topic :: Software Development :: Libraries
License-File: LICENSE
Requires-Dist: aiohttpx
Requires-Dist: backoff
